sibl/sibl
sibl/__init__.py
sibl/templates/role.yml
sibl/templates/project.yml
sibl/templates/host.yml
sibl/templates/group.yml
sibl-0.1.0.data/scripts/sibl
sibl-0.1.0.dist-info/top_level.txt
sibl-0.1.0.dist-info/WHEEL
sibl-0.1.0.dist-info/DESCRIPTION.rst
sibl-0.1.0.dist-info/metadata.json
sibl-0.1.0.dist-info/METADATA
sibl-0.1.0.dist-info/RECORD
